picto/__init__.py
picto/__main__.py
picto/utils.py
picto/cli/__init__.py
picto/cli/snapshot/__init__.py
picto/cli/snapshot/extract.py
picto/cli/snapshot/take.py
picto-0.1.4.dist-info/LICENSE
picto-0.1.4.dist-info/METADATA
picto-0.1.4.dist-info/WHEEL
picto-0.1.4.dist-info/entry_points.txt
picto-0.1.4.dist-info/top_level.txt
picto-0.1.4.dist-info/zip-safe
picto-0.1.4.dist-info/RECORD
